docker_injector/__init__.py
docker_injector/requirements.txt
docker_injector-0.1.9.dist-info/METADATA
docker_injector-0.1.9.dist-info/WHEEL
docker_injector-0.1.9.dist-info/entry_points.txt
docker_injector-0.1.9.dist-info/RECORD
