Metadata-Version: 2.1
Name: docker-injector
Version: 0.1.9
Summary: Docker Injector
Author: Alex MKX
Author-email: github-alex@xxl.cx
Requires-Python: >=3.10,<4.0
Classifier: Programming Language :: Python :: 3
Classifier: Programming Language :: Python :: 3.10
Classifier: Programming Language :: Python :: 3.11
Classifier: Programming Language :: Python :: 3.12
Requires-Dist: click (>=8.1.7,<9.0.0)
Requires-Dist: docker (>=6.1.3,<7.0.0)
